[
  {
    "place_id": "osm_46408584",
    "name": "Boat Ramp",
    "formatted_address": ", Montana, USA",
    "latitude": 47.9944735,
    "longitude": -106.488158,
    "city": "Valley County",
    "county": "",
    "rating": null,
    "total_ratings": 0,
    "types": [
      "leisure_slipway"
    ],
    "business_status": "OPERATIONAL"
  },
  {
    "place_id": "osm_46420935",
    "name": "Boat Ramp",
    "formatted_address": ", Montana, USA",
    "latitude": 48.0157258,
    "longitude": -106.4363175,
    "city": "Valley County",
    "county": "",
    "rating": null,
    "total_ratings": 0,
    "types": [
      "leisure_slipway"
    ],
    "business_status": "OPERATIONAL"
  },
  {
    "place_id": "osm_75852253",
    "name": "Boat Ramp",
    "formatted_address": ", Montana, USA",
    "latitude": 47.0394287,
    "longitude": -104.0094645,
    "city": "Golden Valley County",
    "county": "",
    "rating": null,
    "total_ratings": 0,
    "types": [
      "leisure_slipway"
    ],
    "business_status": "OPERATIONAL"
  },
  {
    "place_id": "osm_314008032",
    "name": "Boat Ramp",
    "formatted_address": ", Montana, USA",
    "latitude": 47.8204222,
    "longitude": -110.6632397,
    "city": "Fort Benton",
    "county": "",
    "rating": null,
    "total_ratings": 0,
    "types": [
      "leisure_slipway"
    ],
    "business_status": "OPERATIONAL"
  },
  {
    "place_id": "osm_470394175",
    "name": "Boat Ramp",
    "formatted_address": ", Montana, USA",
    "latitude": 45.7086352,
    "longitude": -110.3490296,
    "city": "Park County",
    "county": "",
    "rating": null,
    "total_ratings": 0,
    "types": [
      "leisure_slipway"
    ],
    "business_status": "OPERATIONAL"
  },
  {
    "place_id": "osm_793382581",
    "name": "Boat Ramp",
    "formatted_address": ", Montana, USA",
    "latitude": 48.7901444,
    "longitude": -104.5514443,
    "city": "Sheridan County",
    "county": "",
    "rating": null,
    "total_ratings": 0,
    "types": [
      "leisure_slipway"
    ],
    "business_status": "OPERATIONAL"
  },
  {
    "place_id": "osm_1209144814",
    "name": "Boat Ramp",
    "formatted_address": ", Montana, USA",
    "latitude": 44.5334919,
    "longitude": -110.4399793,
    "city": "Teton County",
    "county": "",
    "rating": null,
    "total_ratings": 0,
    "types": [
      "leisure_slipway"
    ],
    "business_status": "OPERATIONAL"
  },
  {
    "place_id": "osm_1642171496",
    "name": "Boat Ramp",
    "formatted_address": ", Montana, USA",
    "latitude": 44.5917442,
    "longitude": -104.4061818,
    "city": "Crook County",
    "county": "",
    "rating": null,
    "total_ratings": 0,
    "types": [
      "leisure_slipway"
    ],
    "business_status": "OPERATIONAL"
  },
  {
    "place_id": "osm_1642171743",
    "name": "Boat Ramp",
    "formatted_address": ", Montana, USA",
    "latitude": 44.5926717,
    "longitude": -104.4066171,
    "city": "Crook County",
    "county": "",
    "rating": null,
    "total_ratings": 0,
    "types": [
      "leisure_slipway"
    ],
    "business_status": "OPERATIONAL"
  },
  {
    "place_id": "osm_1791728276",
    "name": "Boat Ramp",
    "formatted_address": ", Montana, USA",
    "latitude": 46.8041356,
    "longitude": -109.5119389,
    "city": "Fergus County",
    "county": "",
    "rating": null,
    "total_ratings": 0,
    "types": [
      "leisure_slipway"
    ],
    "business_status": "OPERATIONAL"
  },
  {
    "place_id": "osm_1865224668",
    "name": "Boat Ramp",
    "formatted_address": ", Montana, USA",
    "latitude": 44.9433366,
    "longitude": -109.5390599,
    "city": "Park County",
    "county": "",
    "rating": null,
    "total_ratings": 0,
    "types": [
      "leisure_slipway"
    ],
    "business_status": "OPERATIONAL"
  },
  {
    "place_id": "osm_1865226560",
    "name": "Boat Ramp",
    "formatted_address": ", Montana, USA",
    "latitude": 44.94435,
    "longitude": -109.5915346,
    "city": "Park County",
    "county": "",
    "rating": null,
    "total_ratings": 0,
    "types": [
      "leisure_slipway"
    ],
    "business_status": "OPERATIONAL"
  },
  {
    "place_id": "osm_1975132958",
    "name": "Carter'S Bridge Fishing Access",
    "formatted_address": ", Montana, USA",
    "latitude": 45.5973679,
    "longitude": -110.5659769,
    "city": "Park County",
    "county": "",
    "rating": null,
    "total_ratings": 0,
    "types": [
      "leisure_slipway"
    ],
    "business_status": "OPERATIONAL"
  },
  {
    "place_id": "osm_2209515646",
    "name": "James Kipp Campground Boat Ramp",
    "formatted_address": ", Montana, USA",
    "latitude": 47.6238716,
    "longitude": -108.6772508,
    "city": "Fergus County",
    "county": "",
    "rating": null,
    "total_ratings": 0,
    "types": [
      "leisure_slipway"
    ],
    "business_status": "OPERATIONAL"
  },
  {
    "place_id": "osm_2393492809",
    "name": "Carbella",
    "formatted_address": ", Montana, USA",
    "latitude": 45.2122845,
    "longitude": -110.9009755,
    "city": "Park County",
    "county": "",
    "rating": null,
    "total_ratings": 0,
    "types": [
      "leisure_slipway"
    ],
    "business_status": "OPERATIONAL"
  },
  {
    "place_id": "osm_2393492810",
    "name": "Emigrant",
    "formatted_address": ", Montana, USA",
    "latitude": 45.3667852,
    "longitude": -110.725653,
    "city": "Emigrant",
    "county": "",
    "rating": null,
    "total_ratings": 0,
    "types": [
      "leisure_slipway"
    ],
    "business_status": "OPERATIONAL"
  },
  {
    "place_id": "osm_2393492811",
    "name": "Grey Owl",
    "formatted_address": ", Montana, USA",
    "latitude": 45.3975996,
    "longitude": -110.7039625,
    "city": "Park County",
    "county": "",
    "rating": null,
    "total_ratings": 0,
    "types": [
      "leisure_slipway"
    ],
    "business_status": "OPERATIONAL"
  },
  {
    "place_id": "osm_2393492812",
    "name": "Lock Leven",
    "formatted_address": ", Montana, USA",
    "latitude": 45.4636342,
    "longitude": -110.6090244,
    "city": "Park County",
    "county": "",
    "rating": null,
    "total_ratings": 0,
    "types": [
      "leisure_slipway"
    ],
    "business_status": "OPERATIONAL"
  },
  {
    "place_id": "osm_2393492813",
    "name": "Mallards Rest",
    "formatted_address": ", Montana, USA",
    "latitude": 45.4831228,
    "longitude": -110.6204348,
    "city": "Park County",
    "county": "",
    "rating": null,
    "total_ratings": 0,
    "types": [
      "leisure_slipway"
    ],
    "business_status": "OPERATIONAL"
  },
  {
    "place_id": "osm_2393492814",
    "name": "Paradise",
    "formatted_address": ", Montana, USA",
    "latitude": 45.457083,
    "longitude": -110.6248249,
    "city": "Park County",
    "county": "",
    "rating": null,
    "total_ratings": 0,
    "types": [
      "leisure_slipway"
    ],
    "business_status": "OPERATIONAL"
  },
  {
    "place_id": "osm_2393494117",
    "name": "Pine Creek",
    "formatted_address": ", Montana, USA",
    "latitude": 45.5116094,
    "longitude": -110.5827189,
    "city": "Park County",
    "county": "",
    "rating": null,
    "total_ratings": 0,
    "types": [
      "leisure_slipway"
    ],
    "business_status": "OPERATIONAL"
  },
  {
    "place_id": "osm_2614071914",
    "name": "Boat Ramp",
    "formatted_address": ", Montana, USA",
    "latitude": 44.4887639,
    "longitude": -108.0466786,
    "city": "Greybull",
    "county": "",
    "rating": null,
    "total_ratings": 0,
    "types": [
      "leisure_slipway"
    ],
    "business_status": "OPERATIONAL"
  },
  {
    "place_id": "osm_3207689475",
    "name": "Judith Landing BLM Boat Launch",
    "formatted_address": ", Montana, USA",
    "latitude": 47.7387567,
    "longitude": -109.6231584,
    "city": "Chouteau County",
    "county": "",
    "rating": null,
    "total_ratings": 0,
    "types": [
      "leisure_slipway"
    ],
    "business_status": "OPERATIONAL"
  },
  {
    "place_id": "osm_3439765132",
    "name": "Boat Ramp",
    "formatted_address": ", Montana, USA",
    "latitude": 45.2645359,
    "longitude": -110.8094276,
    "city": "Park County",
    "county": "",
    "rating": null,
    "total_ratings": 0,
    "types": [
      "leisure_slipway"
    ],
    "business_status": "OPERATIONAL"
  },
  {
    "place_id": "osm_3516420275",
    "name": "Boat Ramp",
    "formatted_address": ", Montana, USA",
    "latitude": 48.0133916,
    "longitude": -106.4378829,
    "city": "Valley County",
    "county": "",
    "rating": null,
    "total_ratings": 0,
    "types": [
      "leisure_slipway"
    ],
    "business_status": "OPERATIONAL"
  },
  {
    "place_id": "osm_4515142376",
    "name": "Boat Ramp",
    "formatted_address": ", Montana, USA",
    "latitude": 45.758382,
    "longitude": -109.7703891,
    "city": "Sweet Grass County",
    "county": "",
    "rating": null,
    "total_ratings": 0,
    "types": [
      "leisure_slipway"
    ],
    "business_status": "OPERATIONAL"
  },
  {
    "place_id": "osm_4515142620",
    "name": "Boat Ramp",
    "formatted_address": ", Montana, USA",
    "latitude": 45.7181754,
    "longitude": -109.6318825,
    "city": "Sweet Grass County",
    "county": "",
    "rating": null,
    "total_ratings": 0,
    "types": [
      "leisure_slipway"
    ],
    "business_status": "OPERATIONAL"
  },
  {
    "place_id": "osm_4515142660",
    "name": "Boat Ramp",
    "formatted_address": ", Montana, USA",
    "latitude": 45.711868,
    "longitude": -109.5586132,
    "city": "Stillwater County",
    "county": "",
    "rating": null,
    "total_ratings": 0,
    "types": [
      "leisure_slipway"
    ],
    "business_status": "OPERATIONAL"
  },
  {
    "place_id": "osm_4516767803",
    "name": "Boat Ramp",
    "formatted_address": ", Montana, USA",
    "latitude": 45.8540772,
    "longitude": -109.9139315,
    "city": "Sweet Grass County",
    "county": "",
    "rating": null,
    "total_ratings": 0,
    "types": [
      "leisure_slipway"
    ],
    "business_status": "OPERATIONAL"
  },
  {
    "place_id": "osm_4518836260",
    "name": "Boat Ramp",
    "formatted_address": ", Montana, USA",
    "latitude": 45.7897419,
    "longitude": -110.0653726,
    "city": "Sweet Grass County",
    "county": "",
    "rating": null,
    "total_ratings": 0,
    "types": [
      "leisure_slipway"
    ],
    "business_status": "OPERATIONAL"
  },
  {
    "place_id": "osm_4953113830",
    "name": "Boat Ramp",
    "formatted_address": ", Montana, USA",
    "latitude": 47.0407396,
    "longitude": -104.0154406,
    "city": "Golden Valley County",
    "county": "",
    "rating": null,
    "total_ratings": 0,
    "types": [
      "leisure_slipway"
    ],
    "business_status": "OPERATIONAL"
  },
  {
    "place_id": "osm_5703502824",
    "name": "Boat Ramp",
    "formatted_address": ", Montana, USA",
    "latitude": 45.3042864,
    "longitude": -107.9733196,
    "city": "Big Horn County",
    "county": "",
    "rating": null,
    "total_ratings": 0,
    "types": [
      "leisure_slipway"
    ],
    "business_status": "OPERATIONAL"
  },
  {
    "place_id": "osm_7023797654",
    "name": "Boat Ramp",
    "formatted_address": ", Montana, USA",
    "latitude": 44.4502514,
    "longitude": -106.7342965,
    "city": "Johnson County",
    "county": "",
    "rating": null,
    "total_ratings": 0,
    "types": [
      "leisure_slipway"
    ],
    "business_status": "OPERATIONAL"
  },
  {
    "place_id": "osm_7523076109",
    "name": "Boat Ramp",
    "formatted_address": ", Montana, USA",
    "latitude": 48.597042,
    "longitude": -109.9523164,
    "city": "Hill County",
    "county": "",
    "rating": null,
    "total_ratings": 0,
    "types": [
      "leisure_slipway"
    ],
    "business_status": "OPERATIONAL"
  },
  {
    "place_id": "osm_7805262648",
    "name": "Boat Ramp",
    "formatted_address": ", Montana, USA",
    "latitude": 45.7175925,
    "longitude": -110.4668421,
    "city": "Park County",
    "county": "",
    "rating": null,
    "total_ratings": 0,
    "types": [
      "leisure_slipway"
    ],
    "business_status": "OPERATIONAL"
  },
  {
    "place_id": "osm_8133263422",
    "name": "Boat Ramp",
    "formatted_address": ", Montana, USA",
    "latitude": 45.7908747,
    "longitude": -108.4743073,
    "city": "Yellowstone County",
    "county": "",
    "rating": null,
    "total_ratings": 0,
    "types": [
      "leisure_slipway"
    ],
    "business_status": "OPERATIONAL"
  },
  {
    "place_id": "osm_8286291996",
    "name": "Boat Ramp",
    "formatted_address": ", Montana, USA",
    "latitude": 44.7593101,
    "longitude": -107.4375442,
    "city": "Sheridan County",
    "county": "",
    "rating": null,
    "total_ratings": 0,
    "types": [
      "leisure_slipway"
    ],
    "business_status": "OPERATIONAL"
  },
  {
    "place_id": "osm_8461269463",
    "name": "Boat Ramp",
    "formatted_address": ", Montana, USA",
    "latitude": 44.4537091,
    "longitude": -109.1918874,
    "city": "Park County",
    "county": "",
    "rating": null,
    "total_ratings": 0,
    "types": [
      "leisure_slipway"
    ],
    "business_status": "OPERATIONAL"
  },
  {
    "place_id": "osm_8461269464",
    "name": "Boat Ramp",
    "formatted_address": ", Montana, USA",
    "latitude": 44.4568475,
    "longitude": -109.1896509,
    "city": "Park County",
    "county": "",
    "rating": null,
    "total_ratings": 0,
    "types": [
      "leisure_slipway"
    ],
    "business_status": "OPERATIONAL"
  },
  {
    "place_id": "osm_9393296997",
    "name": "Boat Ramp",
    "formatted_address": ", Montana, USA",
    "latitude": 47.1310517,
    "longitude": -104.7031359,
    "city": "Dawson County",
    "county": "",
    "rating": null,
    "total_ratings": 0,
    "types": [
      "leisure_slipway"
    ],
    "business_status": "OPERATIONAL"
  },
  {
    "place_id": "osm_9864415296",
    "name": "Boat Ramp",
    "formatted_address": ", Montana, USA",
    "latitude": 45.3169035,
    "longitude": -107.92075,
    "city": "Big Horn County",
    "county": "",
    "rating": null,
    "total_ratings": 0,
    "types": [
      "leisure_slipway"
    ],
    "business_status": "OPERATIONAL"
  },
  {
    "place_id": "osm_9990780574",
    "name": "Boat Ramp",
    "formatted_address": ", Montana, USA",
    "latitude": 45.8437117,
    "longitude": -108.482097,
    "city": "Billings",
    "county": "",
    "rating": null,
    "total_ratings": 0,
    "types": [
      "leisure_slipway"
    ],
    "business_status": "OPERATIONAL"
  },
  {
    "place_id": "osm_10659681147",
    "name": "Boat Ramp",
    "formatted_address": ", Montana, USA",
    "latitude": 45.6542633,
    "longitude": -108.7572037,
    "city": "Yellowstone County",
    "county": "",
    "rating": null,
    "total_ratings": 0,
    "types": [
      "leisure_slipway"
    ],
    "business_status": "OPERATIONAL"
  },
  {
    "place_id": "osm_11049992833",
    "name": "Boat Ramp",
    "formatted_address": ", Montana, USA",
    "latitude": 45.4852018,
    "longitude": -110.9786803,
    "city": "Gallatin County",
    "county": "",
    "rating": null,
    "total_ratings": 0,
    "types": [
      "leisure_slipway"
    ],
    "business_status": "OPERATIONAL"
  },
  {
    "place_id": "osm_11408765972",
    "name": "Boat Ramp",
    "formatted_address": ", Montana, USA",
    "latitude": 45.8401474,
    "longitude": -108.476915,
    "city": "Billings",
    "county": "",
    "rating": null,
    "total_ratings": 0,
    "types": [
      "leisure_slipway"
    ],
    "business_status": "OPERATIONAL"
  },
  {
    "place_id": "osm_11946134120",
    "name": "Boat Ramp",
    "formatted_address": ", Montana, USA",
    "latitude": 47.9115178,
    "longitude": -110.4928963,
    "city": "Chouteau County",
    "county": "",
    "rating": null,
    "total_ratings": 0,
    "types": [
      "leisure_slipway"
    ],
    "business_status": "OPERATIONAL"
  },
  {
    "place_id": "osm_12356888906",
    "name": "Boat Ramp",
    "formatted_address": ", Montana, USA",
    "latitude": 45.0537409,
    "longitude": -110.7576596,
    "city": "Park County",
    "county": "",
    "rating": null,
    "total_ratings": 0,
    "types": [
      "leisure_slipway"
    ],
    "business_status": "OPERATIONAL"
  },
  {
    "place_id": "osm_12467155987",
    "name": "Boat Ramp",
    "formatted_address": ", Montana, USA",
    "latitude": 45.5378172,
    "longitude": -109.4189331,
    "city": "Stillwater County",
    "county": "",
    "rating": null,
    "total_ratings": 0,
    "types": [
      "leisure_slipway"
    ],
    "business_status": "OPERATIONAL"
  },
  {
    "place_id": "osm_12468243272",
    "name": "Boat Ramp",
    "formatted_address": ", Montana, USA",
    "latitude": 45.1077718,
    "longitude": -110.790208,
    "city": "Park County",
    "county": "",
    "rating": null,
    "total_ratings": 0,
    "types": [
      "leisure_slipway"
    ],
    "business_status": "OPERATIONAL"
  },
  {
    "place_id": "osm_12468243276",
    "name": "Boat Ramp",
    "formatted_address": ", Montana, USA",
    "latitude": 45.1008978,
    "longitude": -110.7819334,
    "city": "Park County",
    "county": "",
    "rating": null,
    "total_ratings": 0,
    "types": [
      "leisure_slipway"
    ],
    "business_status": "OPERATIONAL"
  },
  {
    "place_id": "osm_12468243292",
    "name": "Boat Ramp",
    "formatted_address": ", Montana, USA",
    "latitude": 45.1680506,
    "longitude": -110.8552225,
    "city": "Park County",
    "county": "",
    "rating": null,
    "total_ratings": 0,
    "types": [
      "leisure_slipway"
    ],
    "business_status": "OPERATIONAL"
  },
  {
    "place_id": "osm_12468243297",
    "name": "Boat Ramp",
    "formatted_address": ", Montana, USA",
    "latitude": 45.665917,
    "longitude": -110.5392513,
    "city": "Park County",
    "county": "",
    "rating": null,
    "total_ratings": 0,
    "types": [
      "leisure_slipway"
    ],
    "business_status": "OPERATIONAL"
  },
  {
    "place_id": "osm_12624088372",
    "name": "Boat Ramp",
    "formatted_address": ", Montana, USA",
    "latitude": 45.3155208,
    "longitude": -107.9269462,
    "city": "Big Horn County",
    "county": "",
    "rating": null,
    "total_ratings": 0,
    "types": [
      "leisure_slipway"
    ],
    "business_status": "OPERATIONAL"
  },
  {
    "place_id": "osm_12874182576",
    "name": "Boat Ramp",
    "formatted_address": ", Montana, USA",
    "latitude": 47.2810139,
    "longitude": -104.5266583,
    "city": "Dawson County",
    "county": "",
    "rating": null,
    "total_ratings": 0,
    "types": [
      "leisure_slipway"
    ],
    "business_status": "OPERATIONAL"
  },
  {
    "place_id": "osm_12875427141",
    "name": "Boat Ramp",
    "formatted_address": ", Montana, USA",
    "latitude": 48.0141795,
    "longitude": -106.3614024,
    "city": "McCone County",
    "county": "",
    "rating": null,
    "total_ratings": 0,
    "types": [
      "leisure_slipway"
    ],
    "business_status": "OPERATIONAL"
  },
  {
    "place_id": "osm_12894902585",
    "name": "Boat Ramp",
    "formatted_address": ", Montana, USA",
    "latitude": 45.7436814,
    "longitude": -110.2321162,
    "city": "Park County",
    "county": "",
    "rating": null,
    "total_ratings": 0,
    "types": [
      "leisure_slipway"
    ],
    "business_status": "OPERATIONAL"
  },
  {
    "place_id": "osm_12895507226",
    "name": "Boat Ramp",
    "formatted_address": ", Montana, USA",
    "latitude": 46.8563184,
    "longitude": -105.1148433,
    "city": "Prairie County",
    "county": "",
    "rating": null,
    "total_ratings": 0,
    "types": [
      "leisure_slipway"
    ],
    "business_status": "OPERATIONAL"
  },
  {
    "place_id": "osm_12945511487",
    "name": "Boat Ramp",
    "formatted_address": ", Montana, USA",
    "latitude": 46.2747478,
    "longitude": -106.6788093,
    "city": "Rosebud County",
    "county": "",
    "rating": null,
    "total_ratings": 0,
    "types": [
      "leisure_slipway"
    ],
    "business_status": "OPERATIONAL"
  },
  {
    "place_id": "osm_12951891883",
    "name": "Boat Ramp",
    "formatted_address": ", Montana, USA",
    "latitude": 45.3540511,
    "longitude": -107.8370223,
    "city": "Big Horn County",
    "county": "",
    "rating": null,
    "total_ratings": 0,
    "types": [
      "leisure_slipway"
    ],
    "business_status": "OPERATIONAL"
  },
  {
    "place_id": "osm_12951891925",
    "name": "Boat Ramp",
    "formatted_address": ", Montana, USA",
    "latitude": 45.3441314,
    "longitude": -107.8775791,
    "city": "Big Horn County",
    "county": "",
    "rating": null,
    "total_ratings": 0,
    "types": [
      "leisure_slipway"
    ],
    "business_status": "OPERATIONAL"
  },
  {
    "place_id": "osm_12966418569",
    "name": "Boat Ramp",
    "formatted_address": ", Montana, USA",
    "latitude": 45.6444693,
    "longitude": -107.6583451,
    "city": "Big Horn County",
    "county": "",
    "rating": null,
    "total_ratings": 0,
    "types": [
      "leisure_slipway"
    ],
    "business_status": "OPERATIONAL"
  },
  {
    "place_id": "osm_13195276066",
    "name": "Boat Ramp",
    "formatted_address": ", Montana, USA",
    "latitude": 48.6058016,
    "longitude": -104.1071549,
    "city": "Sheridan County",
    "county": "",
    "rating": null,
    "total_ratings": 0,
    "types": [
      "leisure_slipway"
    ],
    "business_status": "OPERATIONAL"
  },
  {
    "place_id": "osm_28588341",
    "name": "Fort Benton BLM Boat Launch",
    "formatted_address": ", Montana, USA",
    "latitude": 47.8204057,
    "longitude": -110.6633844,
    "city": "Fort Benton",
    "county": "",
    "rating": null,
    "total_ratings": 0,
    "types": [
      "leisure_slipway"
    ],
    "business_status": "OPERATIONAL"
  },
  {
    "place_id": "osm_255728599",
    "name": "Boat Ramp",
    "formatted_address": ", Montana, USA",
    "latitude": 44.4887468,
    "longitude": -108.0465702,
    "city": "Greybull",
    "county": "",
    "rating": null,
    "total_ratings": 0,
    "types": [
      "leisure_slipway"
    ],
    "business_status": "OPERATIONAL"
  },
  {
    "place_id": "osm_320440597",
    "name": "Boat Ramp",
    "formatted_address": ", Montana, USA",
    "latitude": 48.3964881,
    "longitude": -107.7234598,
    "city": "Phillips County",
    "county": "",
    "rating": null,
    "total_ratings": 0,
    "types": [
      "leisure_slipway"
    ],
    "business_status": "OPERATIONAL"
  },
  {
    "place_id": "osm_320440599",
    "name": "Boat Ramp",
    "formatted_address": ", Montana, USA",
    "latitude": 48.4270815,
    "longitude": -107.6836299,
    "city": "Phillips County",
    "county": "",
    "rating": null,
    "total_ratings": 0,
    "types": [
      "leisure_slipway"
    ],
    "business_status": "OPERATIONAL"
  },
  {
    "place_id": "osm_321896034",
    "name": "Boat Ramp",
    "formatted_address": ", Montana, USA",
    "latitude": 48.3707449,
    "longitude": -107.6716365,
    "city": "Phillips County",
    "county": "",
    "rating": null,
    "total_ratings": 0,
    "types": [
      "leisure_slipway"
    ],
    "business_status": "OPERATIONAL"
  },
  {
    "place_id": "osm_327623062",
    "name": "Boat Ramp",
    "formatted_address": ", Montana, USA",
    "latitude": 44.5002914,
    "longitude": -109.2413821,
    "city": "Park County",
    "county": "",
    "rating": null,
    "total_ratings": 0,
    "types": [
      "leisure_slipway"
    ],
    "business_status": "OPERATIONAL"
  },
  {
    "place_id": "osm_331324706",
    "name": "Boat Ramp",
    "formatted_address": ", Montana, USA",
    "latitude": 44.8661216,
    "longitude": -108.1760557,
    "city": "Big Horn County",
    "county": "",
    "rating": null,
    "total_ratings": 0,
    "types": [
      "leisure_slipway"
    ],
    "business_status": "OPERATIONAL"
  },
  {
    "place_id": "osm_332101824",
    "name": "Boat Ramp",
    "formatted_address": ", Montana, USA",
    "latitude": 44.471446,
    "longitude": -109.4187689,
    "city": "Park County",
    "county": "",
    "rating": null,
    "total_ratings": 0,
    "types": [
      "leisure_slipway"
    ],
    "business_status": "OPERATIONAL"
  },
  {
    "place_id": "osm_334156755",
    "name": "Boat Ramp",
    "formatted_address": ", Montana, USA",
    "latitude": 47.6239221,
    "longitude": -108.6774797,
    "city": "Fergus County",
    "county": "",
    "rating": null,
    "total_ratings": 0,
    "types": [
      "leisure_slipway"
    ],
    "business_status": "OPERATIONAL"
  },
  {
    "place_id": "osm_337221591",
    "name": "Boat Ramp",
    "formatted_address": ", Montana, USA",
    "latitude": 47.4306518,
    "longitude": -107.9291751,
    "city": "Petroleum County",
    "county": "",
    "rating": null,
    "total_ratings": 0,
    "types": [
      "leisure_slipway"
    ],
    "business_status": "OPERATIONAL"
  },
  {
    "place_id": "osm_340821052",
    "name": "Boat Ramp",
    "formatted_address": ", Montana, USA",
    "latitude": 47.4649936,
    "longitude": -104.3123462,
    "city": "Richland County",
    "county": "",
    "rating": null,
    "total_ratings": 0,
    "types": [
      "leisure_slipway"
    ],
    "business_status": "OPERATIONAL"
  },
  {
    "place_id": "osm_362670775",
    "name": "Boat Ramp",
    "formatted_address": ", Montana, USA",
    "latitude": 47.6183115,
    "longitude": -107.6539517,
    "city": "Garfield County",
    "county": "",
    "rating": null,
    "total_ratings": 0,
    "types": [
      "leisure_slipway"
    ],
    "business_status": "OPERATIONAL"
  },
  {
    "place_id": "osm_368408560",
    "name": "Boat Ramp",
    "formatted_address": ", Montana, USA",
    "latitude": 47.6183622,
    "longitude": -106.8838124,
    "city": "Garfield County",
    "county": "",
    "rating": null,
    "total_ratings": 0,
    "types": [
      "leisure_slipway"
    ],
    "business_status": "OPERATIONAL"
  },
  {
    "place_id": "osm_404244743",
    "name": "Boat Ramp",
    "formatted_address": ", Montana, USA",
    "latitude": 45.4495639,
    "longitude": -109.2116171,
    "city": "Carbon County",
    "county": "",
    "rating": null,
    "total_ratings": 0,
    "types": [
      "leisure_slipway"
    ],
    "business_status": "OPERATIONAL"
  },
  {
    "place_id": "osm_404244744",
    "name": "Boat Ramp",
    "formatted_address": ", Montana, USA",
    "latitude": 45.4494942,
    "longitude": -109.2115849,
    "city": "Carbon County",
    "county": "",
    "rating": null,
    "total_ratings": 0,
    "types": [
      "leisure_slipway"
    ],
    "business_status": "OPERATIONAL"
  },
  {
    "place_id": "osm_475872615",
    "name": "Boat Ramp",
    "formatted_address": ", Montana, USA",
    "latitude": 46.3300898,
    "longitude": -109.4329492,
    "city": "Wheatland County",
    "county": "",
    "rating": null,
    "total_ratings": 0,
    "types": [
      "leisure_slipway"
    ],
    "business_status": "OPERATIONAL"
  },
  {
    "place_id": "osm_1008714304",
    "name": "Coal Banks Landing Boat Ramp",
    "formatted_address": ", Montana, USA",
    "latitude": 48.0319816,
    "longitude": -110.2355243,
    "city": "Chouteau County",
    "county": "",
    "rating": null,
    "total_ratings": 0,
    "types": [
      "leisure_slipway"
    ],
    "business_status": "OPERATIONAL"
  },
  {
    "place_id": "osm_1230229538",
    "name": "Boat Ramp",
    "formatted_address": ", Montana, USA",
    "latitude": 45.8400334,
    "longitude": -108.4768354,
    "city": "Billings",
    "county": "",
    "rating": null,
    "total_ratings": 0,
    "types": [
      "leisure_slipway"
    ],
    "business_status": "OPERATIONAL"
  },
  {
    "place_id": "osm_1288174284",
    "name": "Woods Bottom BLM Boat Launch",
    "formatted_address": ", Montana, USA",
    "latitude": 47.9114073,
    "longitude": -110.492879,
    "city": "Chouteau County",
    "county": "",
    "rating": null,
    "total_ratings": 0,
    "types": [
      "leisure_slipway"
    ],
    "business_status": "OPERATIONAL"
  },
  {
    "place_id": "osm_1357492973",
    "name": "Boat Ramp",
    "formatted_address": ", Montana, USA",
    "latitude": 44.5895737,
    "longitude": -108.9492568,
    "city": "Park County",
    "county": "",
    "rating": null,
    "total_ratings": 0,
    "types": [
      "leisure_slipway"
    ],
    "business_status": "OPERATIONAL"
  },
  {
    "place_id": "osm_1362646076",
    "name": "Boat Ramp",
    "formatted_address": ", Montana, USA",
    "latitude": 44.480425,
    "longitude": -106.7660556,
    "city": "Johnson County",
    "county": "",
    "rating": null,
    "total_ratings": 0,
    "types": [
      "leisure_slipway"
    ],
    "business_status": "OPERATIONAL"
  },
  {
    "place_id": "osm_1362646082",
    "name": "Boat Ramp",
    "formatted_address": ", Montana, USA",
    "latitude": 44.4507982,
    "longitude": -106.7406105,
    "city": "Johnson County",
    "county": "",
    "rating": null,
    "total_ratings": 0,
    "types": [
      "leisure_slipway"
    ],
    "business_status": "OPERATIONAL"
  },
  {
    "place_id": "osm_1362646153",
    "name": "Boat Ramp",
    "formatted_address": ", Montana, USA",
    "latitude": 44.4547634,
    "longitude": -106.747804,
    "city": "Johnson County",
    "county": "",
    "rating": null,
    "total_ratings": 0,
    "types": [
      "leisure_slipway"
    ],
    "business_status": "OPERATIONAL"
  },
  {
    "place_id": "osm_1363132057",
    "name": "Boat Ramp",
    "formatted_address": ", Montana, USA",
    "latitude": 44.9573911,
    "longitude": -108.2618542,
    "city": "Big Horn County",
    "county": "",
    "rating": null,
    "total_ratings": 0,
    "types": [
      "leisure_slipway"
    ],
    "business_status": "OPERATIONAL"
  },
  {
    "place_id": "osm_1391578663",
    "name": "Boat Ramp",
    "formatted_address": ", Montana, USA",
    "latitude": 47.2051652,
    "longitude": -104.660005,
    "city": "Dawson County",
    "county": "",
    "rating": null,
    "total_ratings": 0,
    "types": [
      "leisure_slipway"
    ],
    "business_status": "OPERATIONAL"
  },
  {
    "place_id": "osm_1434654157",
    "name": "Point Of Rocks",
    "formatted_address": ", Montana, USA",
    "latitude": 45.2535244,
    "longitude": -110.8710464,
    "city": "Park County",
    "county": "",
    "rating": null,
    "total_ratings": 0,
    "types": [
      "leisure_slipway"
    ],
    "business_status": "OPERATIONAL"
  }
]